infty/__init__.py
infty/optim/__init__.py
infty/optim/flat_landscape/__init__.py
infty/optim/flat_landscape/base.py
infty/optim/flat_landscape/c_flat.py
infty/optim/flat_landscape/gam.py
infty/optim/flat_landscape/gsam.py
infty/optim/flat_landscape/looksam.py
infty/optim/flat_landscape/sam.py
infty/optim/gradient_bans/__init__.py
infty/optim/gradient_bans/zeroflow.py
infty/optim/gradient_conflicts/__init__.py
infty/optim/gradient_conflicts/base.py
infty/optim/gradient_conflicts/cagrad.py
infty/optim/gradient_conflicts/gradvac.py
infty/optim/gradient_conflicts/ogd.py
infty/optim/gradient_conflicts/pcgrad.py
infty/optim/gradient_conflicts/unigrad_fs.py
infty/plot/__init__.py
infty/plot/visualize_conflicts.py
infty/plot/visualize_esd.py
infty/plot/visualize_loss_landscape.py
infty/plot/visualize_trajectory.py
infty/utils/hessian.py
infty/utils/memory.py
infty/utils/running.py
infty/utils/schedulers.py
infty-0.1.1.dist-info/LICENSE
infty-0.1.1.dist-info/METADATA
infty-0.1.1.dist-info/WHEEL
infty-0.1.1.dist-info/top_level.txt
infty-0.1.1.dist-info/RECORD
