Metadata-Version: 2.1
Name: infty
Version: 0.1.1
Summary: A continual learning optimizer and visualization toolkit
Home-page: https://github.com/THUDM/INFTY
Author: taofeng weili
Author-email: taofeng weili <ymjiii98@gmail.com>
License: MIT
Keywords: optimization,visualization,machine learning,deep learning
Classifier: Development Status :: 3 - Alpha
Classifier: Intended Audience :: Developers
Classifier: Intended Audience :: Science/Research
Classifier: License :: OSI Approved :: MIT License
Classifier: Operating System :: OS Independent
Classifier: Topic :: Scientific/Engineering :: Artificial Intelligence
Requires-Python: >=3.6
License-File: LICENSE
Requires-Dist: torch>=2.4.0
Requires-Dist: torchvision
Requires-Dist: numpy
Requires-Dist: matplotlib
Requires-Dist: scipy
Requires-Dist: seaborn
Requires-Dist: tqdm
Provides-Extra: examples
Requires-Dist: easydict; extra == "examples"
Requires-Dist: Pillow; extra == "examples"
Requires-Dist: PyYAML; extra == "examples"
Requires-Dist: scikit-learn; extra == "examples"
Requires-Dist: timm>=0.6.13; extra == "examples"
Requires-Dist: umap-learn; extra == "examples"
